imem_ireg/ireg.sv
module instr_reg (
    input  logic        clk,
    input  logic        reset,
    input  logic        en,     // Connect to ~stallD
    input  logic        clear,  // Connect to flushD
    input  logic [31:0] instr_in,
    output logic [31:0] instr_out
);

    always_ff @(posedge clk or posedge reset) begin
        if (reset) begin
            instr_out <= 32'b0;
        end else if (en) begin
            if (clear) 
                instr_out <= 32'b0; // Convert instruction to a NOP
            else 
                instr_out <= instr_in;
        end
    end

endmodule

imem_ireg/imem.sv
module instr_mem #(
    parameter n = 32, 
    parameter r = 8
)(
    input  logic [(r-1):0] addr,
    output logic [(n-1):0] readdata
);

    logic [n-1:0] RAM [0:(2**r)-1];

    initial begin
        // Zero out memory to prevent 'X' in GTKWave for unwritten spots
        for (int i = 0; i < (2**r); i++) begin
            RAM[i] = {n{1'b0}};
        end
        
        // Load the hex file
        $readmemh("test_prog.hex", RAM);
    end

    // 3. Indexing Logic
    // Use addr[(r-1):2] IF PC increments by 4 (Byte-addressed)
    // Use addr[(r-1):0] IF PC increments by 1 (Word-addressed)
    assign readdata = RAM[addr[(r-1):2]];

endmodule

single_cycle_spu/PC.sv
module pc (
    input wire clk,
    input wire reset,
    input wire stall,              // for pipeline (can tie to 0 for now)
    input wire branch_taken,
    input wire [31:0] branch_target,
    output reg [31:0] pc_out
);

wire [31:0] pc_plus4;
assign pc_plus4 = pc_out + 32'd4;

wire [31:0] next_pc;
assign next_pc = branch_taken ? branch_target : pc_plus4;

always @(posedge clk or posedge reset) begin
    if (reset)
        pc_out <= 32'd0;
    else if (!stall)
        pc_out <= next_pc;
end

endmodule

single_cycle_cpu/alu.sv
module alu
    #(parameter bitWidth = 32)(
    input  logic [(bitWidth-1):0] input1, input2,
    input  logic [3:0]  alucontrol,
    output logic [(bitWidth-1):0] result,
    output logic        zero
);

    logic [(bitWidth-1):0] condinvb, sumSlt;

    assign zero = (result == {bitWidth{1'b0}});
    assign condinvb = alucontrol[2] ? ~input2 : input2;
    assign sumSlt = input1 + condinvb + alucontrol[2];

    always @(*) begin
        case (alucontrol)
            4'b0000: result = input1 & input2;              // and
            4'b0001: result = input1 | input2;              // or
            4'b0010: result = input1 + input2;              // add
            4'b0011: result = ~(input1 | input2);           // nor
            4'b0110: result = sumSlt;                       // sub
            4'b0111: begin                                  // slt
                if (input1[31] != input2[31])
                    result = input1[31] ? 1 : 0;
                else
                    result = (input1 < input2) ? 1 : 0;
            end
            // Accumulator: mult/div are fully combinational; ACC receives lower 32 bits, we dont need separate mflo/mfhi instructions
            4'b1000: result = input1 * input2;              // mult (lower 32 bits → ACC)
            4'b1001: result = input1 / input2;              // div  (quotient → ACC)
	    4'b1111: result =  input2; //

            default: result = {bitWidth{1'b0}};
        endcase
    end

endmodule

acc.sv
// ACCUMULATOR 

module acc #(parameter n = 32)(
    input  logic         clk,
    input  logic         reset,
    input  logic         en,      // Write Enable from Controller
    input  logic [n-1:0] d,       // Data from ALU or Memory
    output logic [n-1:0] q        // Current Accumulator Value
);

    always_ff @(posedge clk or posedge reset) begin
        if (reset) 
            q <= {n{1'b0}};
        else if (en) 
            q <= d;
    end

endmodule

aludec.sv
module aludec(
    input  logic [2:0] aluop,
    output logic [3:0] alucontrol
);
    always_comb begin
        case(aluop)
            3'b000:  alucontrol = 4'b0010; // ADD (LDA, ADD)
            3'b001:  alucontrol = 4'b0110; // SUB
            3'b010:  alucontrol = 4'b0000; // AND
            3'b011:  alucontrol = 4'b0001; // OR
            3'b100:  alucontrol = 4'b0111; // SLT
            3'b110:  alucontrol = 4'b1000; // MULT
            3'b111:  alucontrol = 4'b1001; // DIV
            default: alucontrol = 4'b0010; // Default to ADD
        endcase
    end
endmodule

maindec.sv
module maindec(
    input  logic       reset,   // Added reset to kill signals during boot
    input  logic [5:0] op,
    output logic       memtoreg, memwrite,
    output logic       branch, alusrc,
    output logic       regwrite, jump,
    output logic [2:0] aluop
);

    always_comb begin
        if (reset) begin
            // Force everything to 0 during reset
            {regwrite, alusrc, memtoreg, memwrite, branch, jump, aluop} = 9'b0;
        end else begin
            case(op)
                6'h02: {regwrite, alusrc, memtoreg, memwrite, branch, jump, aluop} = 9'b1_1_1_0_0_0_000; // LDA
                6'h06: {regwrite, alusrc, memtoreg, memwrite, branch, jump, aluop} = 9'b1_1_0_0_0_0_000; // ADD
                6'h08: {regwrite, alusrc, memtoreg, memwrite, branch, jump, aluop} = 9'b1_1_0_0_0_0_001; // SUB
                6'h10: {regwrite, alusrc, memtoreg, memwrite, branch, jump, aluop} = 9'b1_1_0_0_0_0_110; // MULT
                6'h12: {regwrite, alusrc, memtoreg, memwrite, branch, jump, aluop} = 9'b1_1_0_0_0_0_111; // DIV
                default: {regwrite, alusrc, memtoreg, memwrite, branch, jump, aluop} = 9'b0_0_0_0_0_0_000; // NOP/Illegal
            endcase
        end
    end
endmodule

fetch_tb.sv
module fetch_tb;

reg clk;
reg reset;
reg stall;
reg branch_taken;
wire [31:0] branch_target;
assign branch_target = 32'b0;

wire [31:0] pc_out;
wire [31:0] instr;
wire [31:0] ir_out;

wire [23:0] immediateD = ir_out[23:0];
wire [5:0]  opcodeD    = ir_out[31:26];
wire [31:0] acc_val;
wire [31:0] alu_out;
wire [31:0] operand2;
// reg         acc_we;

assign operand2 = {8'b0, ir_out[23:0]}; // Zero-extended

// used to test ALU manually
// reg [3:0] manual_alu_control;


// --- Control Signals --- Decoder
wire regwrite, alusrc, memtoreg, memwrite, branch, jump;
wire [2:0] aluop;
wire [3:0] alucontrol;


// --- Main Decoder ---
maindec md (
    .reset(reset),
    .op(opcodeD),
    .regwrite(regwrite),
    .alusrc(alusrc),
    .memtoreg(memtoreg),
    .memwrite(memwrite),
    .branch(branch),
    .jump(jump),
    .aluop(aluop)
);

// --- ALU Decoder ---
aludec ad (
    .aluop(aluop),
    .alucontrol(alucontrol)
);

// --- The Accumulator ---
acc #(.n(32)) main_acc (
    .clk(clk),
    .reset(reset),
    .en(regwrite),      // We'll set this to 1 for this test
    .d(alu_out),
    .q(acc_val)
);

// --- The ALU ---
alu #(.bitWidth(32)) dut_alu (
    .input1(acc_val),  // ACC provides the current running total
    .input2(operand2), // Instruction provides the value to add/sub
    .alucontrol(alucontrol),
    .result(alu_out),
    .zero(alu_zero)
);

// clock
initial begin
    clk = 0;
    forever #5 clk = ~clk;
end

// reset sequence
initial begin
    reset = 1;
    #12 reset = 0;
    #100 $finish;
end

initial begin
    stall = 0;
    branch_taken = 0;
end

// PC
pc pc_inst (
    .clk(clk),
    .reset(reset),
    .stall(stall),
    .branch_taken(branch_taken),
    .branch_target(branch_target),
    .pc_out(pc_out)
);


// Instruction memory
instr_mem imem (
    .addr(pc_out[7:0]),
    .readdata(instr)
);

// Instruction register
instr_reg ir (
    .clk(clk),
    .reset(reset),
    .en(1'b1),      // 1 means "never stall" for now
    .clear(1'b0),   // 0 means "never flush" for now
    .instr_in(instr),
    .instr_out(ir_out)
);

// waveform dump
initial begin
    $dumpfile("fetch.vcd");
    $dumpvars(0, fetch_tb);
end

endmodule

fetch.vcd
$date
	Tue May  5 16:55:45 2026
$end
$version
	Icarus Verilog
$end
$timescale
	1s
$end
$scope module fetch_tb $end
$var wire 32 ! branch_target [31:0] $end
$var wire 1 " regwrite $end
$var wire 32 # pc_out [31:0] $end
$var wire 32 $ operand2 [31:0] $end
$var wire 6 % opcodeD [5:0] $end
$var wire 1 & memwrite $end
$var wire 1 ' memtoreg $end
$var wire 1 ( jump $end
$var wire 32 ) ir_out [31:0] $end
$var wire 32 * instr [31:0] $end
$var wire 24 + immediateD [23:0] $end
$var wire 1 , branch $end
$var wire 1 - alusrc $end
$var wire 3 . aluop [2:0] $end
$var wire 4 / alucontrol [3:0] $end
$var wire 1 0 alu_zero $end
$var wire 32 1 alu_out [31:0] $end
$var wire 32 2 acc_val [31:0] $end
$var reg 1 3 branch_taken $end
$var reg 1 4 clk $end
$var reg 1 5 reset $end
$var reg 1 6 stall $end
$scope module ad $end
$var wire 3 7 aluop [2:0] $end
$var reg 4 8 alucontrol [3:0] $end
$upscope $end
$scope module dut_alu $end
$var wire 4 9 alucontrol [3:0] $end
$var wire 32 : input2 [31:0] $end
$var wire 1 0 zero $end
$var wire 32 ; sumSlt [31:0] $end
$var wire 32 < input1 [31:0] $end
$var wire 32 = condinvb [31:0] $end
$var parameter 32 > bitWidth $end
$var reg 32 ? result [31:0] $end
$upscope $end
$scope module imem $end
$var wire 8 @ addr [7:0] $end
$var wire 32 A readdata [31:0] $end
$var parameter 32 B n $end
$var parameter 32 C r $end
$scope begin $ivl_for_loop0 $end
$var integer 32 D i [31:0] $end
$upscope $end
$upscope $end
$scope module ir $end
$var wire 1 E clear $end
$var wire 1 4 clk $end
$var wire 1 F en $end
$var wire 32 G instr_in [31:0] $end
$var wire 1 5 reset $end
$var reg 32 H instr_out [31:0] $end
$upscope $end
$scope module main_acc $end
$var wire 1 4 clk $end
$var wire 32 I d [31:0] $end
$var wire 1 5 reset $end
$var wire 1 " en $end
$var parameter 32 J n $end
$var reg 32 K q [31:0] $end
$upscope $end
$scope module md $end
$var wire 6 L op [5:0] $end
$var wire 1 5 reset $end
$var reg 3 M aluop [2:0] $end
$var reg 1 - alusrc $end
$var reg 1 , branch $end
$var reg 1 ( jump $end
$var reg 1 ' memtoreg $end
$var reg 1 & memwrite $end
$var reg 1 " regwrite $end
$upscope $end
$scope module pc_inst $end
$var wire 1 3 branch_taken $end
$var wire 32 N branch_target [31:0] $end
$var wire 1 4 clk $end
$var wire 1 5 reset $end
$var wire 1 6 stall $end
$var wire 32 O pc_plus4 [31:0] $end
$var wire 32 P next_pc [31:0] $end
$var reg 32 Q pc_out [31:0] $end
$upscope $end
$upscope $end
$enddefinitions $end
$comment Show the parameter values. $end
$dumpall
b100000 J
b1000 C
b100000 B
b100000 >
$end
#0
$dumpvars
b0 Q
b100 P
b100 O
b0 N
b0 M
b0 L
b0 K
b0 I
b0 H
b100000000000000000000000001010 G
1F
0E
b100000000 D
b100000000000000000000000001010 A
b0 @
b0 ?
b0 =
b0 <
b0 ;
b0 :
b10 9
b10 8
b0 7
06
15
04
03
b0 2
b0 1
10
b10 /
b0 .
0-
0,
b0 +
b100000000000000000000000001010 *
b0 )
0(
0'
0&
b0 %
b0 $
b0 #
0"
b0 !
$end
#5
14
#10
04
#12
05
#15
b110 /
b110 8
b110 9
b1000000000000000000000000010 *
b1000000000000000000000000010 A
b1000000000000000000000000010 G
00
b11111111111111111111111111110110 1
b11111111111111111111111111110110 ?
b11111111111111111111111111110110 I
b11111111111111111111111111110110 ;
b11111111111111111111111111110101 =
1"
1-
b1 .
b1 7
b1 M
b1000 P
b100 @
b1010 $
b1010 :
b1000 %
b1000 L
b1010 +
b1000 O
b100 #
b100 Q
b100000000000000000000000001010 )
b100000000000000000000000001010 H
14
#20
04
#25
b10 =
b10 /
b10 8
b10 9
1'
b0 .
b0 7
b0 M
b1000000000000000000000000000011 *
b1000000000000000000000000000011 A
b1000000000000000000000000000011 G
b10 $
b10 :
b10 %
b10 L
b10 +
b1100 P
b1000 @
b11111111111111111111111111111000 1
b11111111111111111111111111111000 ?
b11111111111111111111111111111000 I
b1000000000000000000000000010 )
b1000000000000000000000000010 H
b1100 O
b1000 #
b1000 Q
b11111111111111111111111111111000 ;
b11111111111111111111111111110110 2
b11111111111111111111111111110110 <
b11111111111111111111111111110110 K
14
#30
04
#35
b1000 /
b1000 8
b1000 9
b1001000000000000000000000000110 *
b1001000000000000000000000000110 A
b1001000000000000000000000000110 G
b11 =
0'
b110 .
b110 7
b110 M
b11111111111111111111111111101000 1
b11111111111111111111111111101000 ?
b11111111111111111111111111101000 I
b10000 P
b1100 @
b11 $
b11 :
b10000 %
b10000 L
b11 +
b11111111111111111111111111111011 ;
b11111111111111111111111111111000 2
b11111111111111111111111111111000 <
b11111111111111111111111111111000 K
b10000 O
b1100 #
b1100 Q
b1000000000000000000000000000011 )
b1000000000000000000000000000011 H
14
#40
04
#45
b1001 /
b1001 8
b1001 9
b110 =
b111 .
b111 7
b111 M
b0 *
b0 A
b0 G
b110 $
b110 :
b10010 %
b10010 L
b110 +
b10100 P
b10000 @
b101010101010101010101010100110 1
b101010101010101010101010100110 ?
b101010101010101010101010100110 I
b1001000000000000000000000000110 )
b1001000000000000000000000000110 H
b10100 O
b10000 #
b10000 Q
b11111111111111111111111111101110 ;
b11111111111111111111111111101000 2
b11111111111111111111111111101000 <
b11111111111111111111111111101000 K
14
#50
04
#55
b10 /
b10 8
b10 9
b0 =
0"
0-
b0 .
b0 7
b0 M
00
b101010101010101010101010100110 1
b101010101010101010101010100110 ?
b101010101010101010101010100110 I
b11000 P
b10100 @
b0 $
b0 :
b0 %
b0 L
b0 +
b101010101010101010101010100110 ;
b101010101010101010101010100110 2
b101010101010101010101010100110 <
b101010101010101010101010100110 K
b11000 O
b10100 #
b10100 Q
b0 )
b0 H
14
#60
04
#65
b11100 P
b11000 @
b11100 O
b11000 #
b11000 Q
14
#70
04
#75
b100000 P
b11100 @
b100000 O
b11100 #
b11100 Q
14
#80
04
#85
b100100 P
b100000 @
b100100 O
b100000 #
b100000 Q
14
#90
04
#95
b101000 P
b100100 @
b101000 O
b100100 #
b100100 Q
14
#100
04
#105
b101100 P
b101000 @
b101100 O
b101000 #
b101000 Q
14
