imem_ireg/ireg.sv
module instr_reg (
    input  logic        clk,
    input  logic        reset,
    input  logic        en,     // Connect to ~stallD
    input  logic        clear,  // Connect to flushD
    input  logic [31:0] instr_in,
    output logic [31:0] instr_out
);

    always_ff @(posedge clk or posedge reset) begin
        if (reset) begin
            instr_out <= 32'b0;
        end else if (en) begin
            if (clear) 
                instr_out <= 32'b0; // Convert instruction to a NOP
            else 
                instr_out <= instr_in;
        end
    end

endmodule

imem_ireg/imem.sv
module instr_mem #(
    parameter n = 32, 
    parameter r = 8
)(
    input  logic [(r-1):0] addr,
    output logic [(n-1):0] readdata
);

    logic [n-1:0] RAM [0:(2**r)-1];

    initial begin
        // Zero out memory to prevent 'X' in GTKWave for unwritten spots
        for (int i = 0; i < (2**r); i++) begin
            RAM[i] = {n{1'b0}};
        end
        
        // Load the hex file
        $readmemh("test_prog.hex", RAM);
    end

    // 3. Indexing Logic
    // Use addr[(r-1):2] IF PC increments by 4 (Byte-addressed)
    // Use addr[(r-1):0] IF PC increments by 1 (Word-addressed)
    assign readdata = RAM[addr[(r-1):2]];

endmodule

PC/PC.sv
module pc (
    input wire clk,
    input wire reset,
    input wire stall,              // for pipeline (can tie to 0 for now)
    input wire branch_taken,
    input wire [31:0] branch_target,
    output reg [31:0] pc_out
);

wire [31:0] pc_plus4;
assign pc_plus4 = pc_out + 32'd4;

wire [31:0] next_pc;
assign next_pc = branch_taken ? branch_target : pc_plus4;

always @(posedge clk or posedge reset) begin
    if (reset)
        pc_out <= 32'd0;
    else if (!stall)
        pc_out <= next_pc;
end

endmodule

fetch_tb.sv
module fetch_tb;

reg clk;
reg reset;
reg stall;
reg branch_taken;
wire [31:0] branch_target;
assign branch_target = 32'b0;

wire [31:0] pc_out;
wire [31:0] instr;
wire [31:0] ir_out;

// clock
initial begin
    clk = 0;
    forever #5 clk = ~clk;
end

// reset sequence
initial begin
    reset = 1;
    #12 reset = 0;
    #100 $finish;
end

initial begin
    stall = 0;
    branch_taken = 0;
end

// PC
pc pc_inst (
    .clk(clk),
    .reset(reset),
    .stall(stall),
    .branch_taken(branch_taken),
    .branch_target(branch_target),
    .pc_out(pc_out)
);

// Instruction memory
instr_mem imem (
    .addr(pc_out[7:0]),
    .readdata(instr)
);

// Instruction register
instr_reg ir (
    .clk(clk),
    .reset(reset),
    .en(1'b1),      // 1 means "never stall" for now
    .clear(1'b0),   // 0 means "never flush" for now
    .instr_in(instr),
    .instr_out(ir_out)
);

// waveform dump
initial begin
    $dumpfile("fetch.vcd");
    $dumpvars(0, fetch_tb);
end

endmodule

fetch.vcd
$date
	Tue May  5 15:24:38 2026
$end
$version
	Icarus Verilog
$end
$timescale
	1s
$end
$scope module fetch_tb $end
$var wire 32 ! branch_target [31:0] $end
$var wire 32 " pc_out [31:0] $end
$var wire 32 # ir_out [31:0] $end
$var wire 32 $ instr [31:0] $end
$var reg 1 % branch_taken $end
$var reg 1 & clk $end
$var reg 1 ' reset $end
$var reg 1 ( stall $end
$scope module imem $end
$var wire 8 ) addr [7:0] $end
$var wire 32 * readdata [31:0] $end
$var parameter 32 + n $end
$var parameter 32 , r $end
$scope begin $ivl_for_loop0 $end
$var integer 32 - i [31:0] $end
$upscope $end
$upscope $end
$scope module ir $end
$var wire 1 . clear $end
$var wire 1 & clk $end
$var wire 1 / en $end
$var wire 32 0 instr_in [31:0] $end
$var wire 1 ' reset $end
$var reg 32 1 instr_out [31:0] $end
$upscope $end
$scope module pc_inst $end
$var wire 1 % branch_taken $end
$var wire 32 2 branch_target [31:0] $end
$var wire 1 & clk $end
$var wire 1 ' reset $end
$var wire 1 ( stall $end
$var wire 32 3 pc_plus4 [31:0] $end
$var wire 32 4 next_pc [31:0] $end
$var reg 32 5 pc_out [31:0] $end
$upscope $end
$upscope $end
$enddefinitions $end
$comment Show the parameter values. $end
$dumpall
b1000 ,
b100000 +
$end
#0
$dumpvars
b0 5
b100 4
b100 3
b0 2
b0 1
b10101010101110111100110011011101 0
1/
0.
b100000000 -
b10101010101110111100110011011101 *
b0 )
0(
1'
0&
0%
b10101010101110111100110011011101 $
b0 #
b0 "
b0 !
$end
#5
1&
#10
0&
#12
0'
#15
b10001001000100011001101000100 $
b10001001000100011001101000100 *
b10001001000100011001101000100 0
b1000 4
b100 )
b1000 3
b100 "
b100 5
b10101010101110111100110011011101 #
b10101010101110111100110011011101 1
1&
#20
0&
#25
b1010101011001100111011110001000 $
b1010101011001100111011110001000 *
b1010101011001100111011110001000 0
b1100 4
b1000 )
b10001001000100011001101000100 #
b10001001000100011001101000100 1
b1100 3
b1000 "
b1000 5
1&
#30
0&
#35
b10011001000000001010101010111011 $
b10011001000000001010101010111011 *
b10011001000000001010101010111011 0
b10000 4
b1100 )
b10000 3
b1100 "
b1100 5
b1010101011001100111011110001000 #
b1010101011001100111011110001000 1
1&
#40
0&
#45
b0 $
b0 *
b0 0
b10100 4
b10000 )
b10011001000000001010101010111011 #
b10011001000000001010101010111011 1
b10100 3
b10000 "
b10000 5
1&
#50
0&
#55
b11000 4
b10100 )
b11000 3
b10100 "
b10100 5
b0 #
b0 1
1&
#60
0&
#65
b11100 4
b11000 )
b11100 3
b11000 "
b11000 5
1&
#70
0&
#75
b100000 4
b11100 )
b100000 3
b11100 "
b11100 5
1&
#80
0&
#85
b100100 4
b100000 )
b100100 3
b100000 "
b100000 5
1&
#90
0&
#95
b101000 4
b100100 )
b101000 3
b100100 "
b100100 5
1&
#100
0&
#105
b101100 4
b101000 )
b101100 3
b101000 "
b101000 5
1&
