imem_ireg/ireg.sv
module instr_reg (
    input  logic        clk,
    input  logic        reset,
    input  logic        en,     // Connect to ~stallD
    input  logic        clear,  // Connect to flushD
    input  logic [31:0] instr_in,
    output logic [31:0] instr_out
);

    always_ff @(posedge clk or posedge reset) begin
        if (reset) begin
            instr_out <= 32'b0;
        end else if (en) begin
            if (clear) 
                instr_out <= 32'b0; // Convert instruction to a NOP
            else 
                instr_out <= instr_in;
        end
    end

endmodule

imem_ireg/imem.sv
module instr_mem #(
    parameter n = 32, 
    parameter r = 8
)(
    input  logic [(r-1):0] addr,
    output logic [(n-1):0] readdata
);

    logic [n-1:0] RAM [0:(2**r)-1];

    initial begin
        // Zero out memory to prevent 'X' in GTKWave for unwritten spots
        for (int i = 0; i < (2**r); i++) begin
            RAM[i] = {n{1'b0}};
        end
        
        // Load the hex file
        $readmemh("test_prog.hex", RAM);
    end

    // 3. Indexing Logic
    // Use addr[(r-1):2] IF PC increments by 4 (Byte-addressed)
    // Use addr[(r-1):0] IF PC increments by 1 (Word-addressed)
    assign readdata = RAM[addr[(r-1):2]];

endmodule

single_cycle_spu/PC.sv
module pc (
    input wire clk,
    input wire reset,
    input wire stall,              // for pipeline (can tie to 0 for now)
    input wire branch_taken,
    input wire [31:0] branch_target,
    output reg [31:0] pc_out
);

wire [31:0] pc_plus4;
assign pc_plus4 = pc_out + 32'd4;

wire [31:0] next_pc;
assign next_pc = branch_taken ? branch_target : pc_plus4;

always @(posedge clk or posedge reset) begin
    if (reset)
        pc_out <= 32'd0;
    else if (!stall)
        pc_out <= next_pc;
end

endmodule

dmem.sv
module dmem(
    input  logic        clk,
    input  logic        we,   // memwrite from maindec
    input  logic [31:0] a,    // address from alu_out
    input  logic [31:0] wd,   // write data from acc_val
    output logic [31:0] rd    // read data
);

  logic [31:0] RAM[63:0]; // 64 words of memory

  // Read is combinational
  assign rd = RAM[a[31:2]]; 

  // Write is synchronous
  always_ff @(posedge clk)
    if (we) RAM[a[31:2]] <= wd;

endmodule

single_cycle_cpu/alu.sv
module alu
    #(parameter bitWidth = 32)(
    input  logic [(bitWidth-1):0] input1, input2,
    input  logic [3:0]  alucontrol,
    output logic [(bitWidth-1):0] result,
    output logic        zero
);

    logic [(bitWidth-1):0] condinvb, sumSlt;

    assign zero = (result == {bitWidth{1'b0}});
    assign condinvb = alucontrol[2] ? ~input2 : input2;
    assign sumSlt = input1 + condinvb + alucontrol[2];

    always @(*) begin
        case (alucontrol)
            4'b0000: result = input1 & input2;              // and
            4'b0001: result = input1 | input2;              // or
            4'b0010: result = input1 + input2;              // add
            4'b0011: result = ~(input1 | input2);           // nor
            4'b0110: result = sumSlt;                       // sub
            4'b0111: begin                                  // slt
                if (input1[31] != input2[31])
                    result = input1[31] ? 1 : 0;
                else
                    result = (input1 < input2) ? 1 : 0;
            end
            // Accumulator: mult/div are fully combinational; ACC receives lower 32 bits, we dont need separate mflo/mfhi instructions
            4'b1000: result = input1 * input2;              // mult (lower 32 bits → ACC)
            4'b1001: result = input1 / input2;              // div  (quotient → ACC)
	    4'b1111: result =  input2; //

            default: result = {bitWidth{1'b0}};
        endcase
    end

endmodule

acc.sv
// ACCUMULATOR 

module acc #(parameter n = 32)(
    input  logic         clk,
    input  logic         reset,
    input  logic         en,      // Write Enable from Controller
    input  logic [n-1:0] d,       // Data from ALU or Memory
    output logic [n-1:0] q        // Current Accumulator Value
);

    always_ff @(posedge clk or posedge reset) begin
        if (reset) 
            q <= {n{1'b0}};
        else if (en) 
            q <= d;
    end

endmodule

aludec.sv
module aludec(
    input  logic [1:0] aluop,
    output logic [3:0] alucontrol
);

    always_comb begin
        case (aluop)
            2'b00: alucontrol = 4'b0010; // ADD
            2'b01: alucontrol = 4'b0110; // SUB (used for branch comparison)
            2'b10: alucontrol = 4'b1000; // MULT
            2'b11: alucontrol = 4'b1001; // DIV
            default: alucontrol = 4'b0010;
        endcase
    end
endmodule

maindec.sv
module maindec(
    input  logic       reset,
    input  logic [5:0] op,
    output logic       memtoreg, memwrite,
    output logic       branch, alusrc,
    output logic       regwrite, jump,
    output logic [1:0] aluop 
);
    logic [7:0] controls;
    assign {regwrite, alusrc, memtoreg, memwrite, branch, jump, aluop} = controls;

    always_comb begin
        if (reset) controls = 8'b00000000;
        else begin
            case(op)
                // alusrc=0 ensures check Acc, not Acc vs Offset
                6'h04:   controls = 8'b0_0_0_0_1_0_00; // BZ
                6'h08:   controls = 8'b1_1_1_0_0_0_00; // LDA
                6'h02:   controls = 8'b1_1_0_0_0_0_00; // ADD
                6'h10:   controls = 8'b1_1_0_0_0_0_10; // MULT
                6'h12:   controls = 8'b1_1_0_0_0_0_11; // DIV
                6'h2B:   controls = 8'b0_1_0_1_0_0_00; // STA
                default: controls = 8'b0_0_0_0_0_0_00; // NOP
            endcase
        end
    end
endmodule

fetch_tb.sv
module fetch_tb;

    reg clk;
    reg reset;
    reg stall;
    reg zero_reg; // Sequential register to bridge the timing gap

    // --- Branch & Control Signals ---
    wire branch_taken;      
    wire [31:0] branch_target;
    wire alu_zero;          
    wire regwrite, alusrc, memtoreg, memwrite, branch, jump;
    wire [1:0] aluop;       
    wire [3:0] alucontrol;  

    // --- Data & Instruction Wires ---
    wire [31:0] pc_out;
    wire [31:0] instr;
    wire [31:0] ir_out;
    wire [31:0] acc_val;
    wire [31:0] alu_out;
    wire [31:0] operand2;
    wire [31:0] read_data; 
    wire [31:0] imm_ext;

    // --- Combinational Logic ---
    wire [23:0] immediateD = ir_out[23:0];
    wire [5:0]  opcodeD    = ir_out[31:26];

    // BZ and BNZ logic
    wire is_bz = (opcodeD == 6'h04);
    wire is_bnz = (opcodeD == 6'h05);

    assign branch_taken = (is_bz && zero_reg) || (is_bnz && !zero_reg);

    // Sign-extend immediate and calculate target
    assign imm_ext = {{8{immediateD[23]}}, immediateD};
    assign branch_target = (pc_out + 4) + (imm_ext << 2);

    // Operand2 Multiplexer (ALUSRC logic)
    assign operand2 = alusrc ? {{8{ir_out[23]}}, ir_out[23:0]} : 32'b0;

    // --- Module Instantiations ---

    maindec md (
        .reset(reset),
        .op(opcodeD),
        .regwrite(regwrite),
        .alusrc(alusrc),
        .memtoreg(memtoreg),
        .memwrite(memwrite),
        .branch(branch),
        .jump(jump),
        .aluop(aluop)
    );

    aludec ad (
        .aluop(aluop),
        .alucontrol(alucontrol)
    );

    acc #(.n(32)) main_acc (
        .clk(clk),
        .reset(reset),
        .en(regwrite),
        .d(alu_out),
        .q(acc_val)
    );

    alu #(.bitWidth(32)) dut_alu (
        .input1(acc_val),
        .input2(operand2),
        .alucontrol(alucontrol),
        .result(alu_out),
        .zero(alu_zero)
    );

    dmem data_mem (
        .clk(clk),
        .we(memwrite),
        .a(alu_out),
        .wd(acc_val),
        .rd(read_data)
    );

    pc pc_inst (
        .clk(clk),
        .reset(reset),
        .stall(stall),
        .branch_taken(branch_taken),
        .branch_target(branch_target),
        .pc_out(pc_out)
    );

    instr_mem imem (
        .addr(pc_out[7:0]),
        .readdata(instr)
    );

    instr_reg ir (
        .clk(clk),
        .reset(reset),
        .en(1'b1),
        .clear(1'b0),
        .instr_in(instr),
        .instr_out(ir_out)
    );

    // --- Clock & Reset Generation ---

    initial begin
        clk = 0;
        forever #5 clk = ~clk;
    end

    initial begin
        reset = 1;
        stall = 0;
        #12 reset = 0;
        #300 $finish;
    end

    // --- Logic for Flag Synchronization ---

    always @(posedge clk or posedge reset) begin
        if (reset) 
            zero_reg <= 0;
        else
            zero_reg <= alu_zero; 
    end

// --- Enhanced Debug Logging ---
initial begin
    $display("\nTime | PC_OUT   | IR_OUT   | ACC_VAL  | ALU_OUT  | REGW | BR | ZERO_R | TAKEN | TARGET");
    $display("------------------------------------------------------------------------------------------");
    forever @(negedge clk) begin // Logging on negedge captures values after the clock transition
        $display("%4t | %h | %h | %h | %h |  %b   | %b  |   %b    |   %b   | %h", 
            $time, 
            pc_out, 
            ir_out, 
            acc_val, 
            alu_out, 
            regwrite, 
            branch, 
            zero_reg, 
            branch_taken, 
            branch_target
        );
    end
end

    initial begin
        $dumpfile("fetch.vcd");
        $dumpvars(0, fetch_tb);
    end

endmodule

fetch.vcd
$date
	Wed May  6 21:54:20 2026
$end
$version
	Icarus Verilog
$end
$timescale
	1s
$end
$scope module fetch_tb $end
$var wire 1 ! branch_taken $end
$var wire 1 " regwrite $end
$var wire 32 # read_data [31:0] $end
$var wire 32 $ pc_out [31:0] $end
$var wire 32 % operand2 [31:0] $end
$var wire 6 & opcodeD [5:0] $end
$var wire 1 ' memwrite $end
$var wire 1 ( memtoreg $end
$var wire 1 ) jump $end
$var wire 1 * is_bz $end
$var wire 1 + is_bnz $end
$var wire 32 , ir_out [31:0] $end
$var wire 32 - instr [31:0] $end
$var wire 24 . immediateD [23:0] $end
$var wire 32 / imm_ext [31:0] $end
$var wire 32 0 branch_target [31:0] $end
$var wire 1 1 branch $end
$var wire 1 2 alusrc $end
$var wire 2 3 aluop [1:0] $end
$var wire 4 4 alucontrol [3:0] $end
$var wire 1 5 alu_zero $end
$var wire 32 6 alu_out [31:0] $end
$var wire 32 7 acc_val [31:0] $end
$var reg 1 8 clk $end
$var reg 1 9 reset $end
$var reg 1 : stall $end
$var reg 1 ; zero_reg $end
$scope module ad $end
$var wire 2 < aluop [1:0] $end
$var reg 4 = alucontrol [3:0] $end
$upscope $end
$scope module data_mem $end
$var wire 1 8 clk $end
$var wire 32 > rd [31:0] $end
$var wire 1 ' we $end
$var wire 32 ? wd [31:0] $end
$var wire 32 @ a [31:0] $end
$upscope $end
$scope module dut_alu $end
$var wire 4 A alucontrol [3:0] $end
$var wire 32 B input2 [31:0] $end
$var wire 1 5 zero $end
$var wire 32 C sumSlt [31:0] $end
$var wire 32 D input1 [31:0] $end
$var wire 32 E condinvb [31:0] $end
$var parameter 32 F bitWidth $end
$var reg 32 G result [31:0] $end
$upscope $end
$scope module imem $end
$var wire 8 H addr [7:0] $end
$var wire 32 I readdata [31:0] $end
$var parameter 32 J n $end
$var parameter 32 K r $end
$scope begin $ivl_for_loop0 $end
$var integer 32 L i [31:0] $end
$upscope $end
$upscope $end
$scope module ir $end
$var wire 1 M clear $end
$var wire 1 8 clk $end
$var wire 1 N en $end
$var wire 32 O instr_in [31:0] $end
$var wire 1 9 reset $end
$var reg 32 P instr_out [31:0] $end
$upscope $end
$scope module main_acc $end
$var wire 1 8 clk $end
$var wire 32 Q d [31:0] $end
$var wire 1 9 reset $end
$var wire 1 " en $end
$var parameter 32 R n $end
$var reg 32 S q [31:0] $end
$upscope $end
$scope module md $end
$var wire 6 T op [5:0] $end
$var wire 1 9 reset $end
$var wire 1 " regwrite $end
$var wire 1 ' memwrite $end
$var wire 1 ( memtoreg $end
$var wire 1 ) jump $end
$var wire 1 1 branch $end
$var wire 1 2 alusrc $end
$var wire 2 U aluop [1:0] $end
$var reg 8 V controls [7:0] $end
$upscope $end
$scope module pc_inst $end
$var wire 1 ! branch_taken $end
$var wire 32 W branch_target [31:0] $end
$var wire 1 8 clk $end
$var wire 1 9 reset $end
$var wire 1 : stall $end
$var wire 32 X pc_plus4 [31:0] $end
$var wire 32 Y next_pc [31:0] $end
$var reg 32 Z pc_out [31:0] $end
$upscope $end
$upscope $end
$enddefinitions $end
$comment Show the parameter values. $end
$dumpall
b100000 R
b1000 K
b100000 J
b100000 F
$end
#0
$dumpvars
b0 Z
b100 Y
b100 X
b100 W
b0 V
b0 U
b0 T
b0 S
b0 Q
b0 P
b100000000000000000000000000101 O
1N
0M
b100000000 L
b100000000000000000000000000101 I
b0 H
b0 G
b0 E
b0 D
b0 C
b0 B
b10 A
b0 @
b0 ?
bx >
b10 =
b0 <
x;
0:
19
08
b0 7
b0 6
15
b10 4
b0 3
02
01
b100 0
b0 /
b0 .
b100000000000000000000000000101 -
b0 ,
0+
0*
0)
0(
0'
b0 &
b0 %
b0 $
bx #
0"
0!
$end
#5
0;
18
#10
08
#12
09
#15
05
b101 6
b101 @
b101 G
b101 Q
b101 C
b101 E
b101 %
b101 B
1"
12
1(
b1000111111111111111111111111 -
b1000111111111111111111111111 I
b1000111111111111111111111111 O
b11100000 V
b1000 Y
b100 H
b1000 &
b1000 T
b101 /
b101 .
b1000 X
b11100 0
b11100 W
b100 $
b100 Z
b100000000000000000000000000101 ,
b100000000000000000000000000101 P
1;
18
#20
08
#25
b11111111111111111111111111111111 E
0(
b11111111111111111111111111111111 %
b11111111111111111111111111111111 B
b11000000 V
b0 -
b0 I
b0 O
b10 &
b10 T
b11111111111111111111111111111111 /
b111111111111111111111111 .
b1100 Y
b1000 H
b100 6
b100 @
b100 G
b100 Q
0;
b1000111111111111111111111111 ,
b1000111111111111111111111111 P
b1100 X
b1000 0
b1000 W
b1000 $
b1000 Z
b100 C
b101 7
b101 ?
b101 D
b101 S
18
#30
08
#35
b0 E
0"
02
b0 %
b0 B
b0 V
b100 6
b100 @
b100 G
b100 Q
b10000 Y
b1100 H
b0 &
b0 T
b0 /
b0 .
b100 C
b100 7
b100 ?
b100 D
b100 S
b10000 X
b10000 0
b10000 W
b1100 $
b1100 Z
b0 ,
b0 P
18
#40
08
#45
b10100 Y
b10000 H
b10100 X
b10100 0
b10100 W
b10000 $
b10000 Z
18
#50
08
#55
b10100111111111111111111111010 -
b10100111111111111111111111010 I
b10100111111111111111111111010 O
b11000 Y
b10100 H
b11000 X
b11000 0
b11000 W
b10100 $
b10100 Z
18
#60
08
#65
1!
11
b1000 V
b0 -
b0 I
b0 O
1+
b101 &
b101 T
b11111111111111111111111111111010 /
b111111111111111111111010 .
b100 Y
b11000 H
b10100111111111111111111111010 ,
b10100111111111111111111111010 P
b11100 X
b100 0
b100 W
b11000 $
b11000 Z
18
#70
08
#75
0!
01
b1000111111111111111111111111 -
b1000111111111111111111111111 I
b1000111111111111111111111111 O
b0 V
b100 H
b1000 Y
0+
b0 &
b0 T
b0 /
b0 .
b1000 X
b1000 0
b1000 W
b100 $
b100 Z
b0 ,
b0 P
18
#80
08
#85
b11 6
b11 @
b11 G
b11 Q
b11 C
b11111111111111111111111111111111 E
b11111111111111111111111111111111 %
b11111111111111111111111111111111 B
1"
12
b11000000 V
b0 -
b0 I
b0 O
b10 &
b10 T
b11111111111111111111111111111111 /
b111111111111111111111111 .
b1100 Y
b1000 H
b1000111111111111111111111111 ,
b1000111111111111111111111111 P
b1100 X
b1000 0
b1000 W
b1000 $
b1000 Z
18
#90
08
#95
b0 E
0"
02
b0 %
b0 B
b0 V
b11 6
b11 @
b11 G
b11 Q
b10000 Y
b1100 H
b0 &
b0 T
b0 /
b0 .
b11 C
b11 7
b11 ?
b11 D
b11 S
b10000 X
b10000 0
b10000 W
b1100 $
b1100 Z
b0 ,
b0 P
18
#100
08
#105
b10100 Y
b10000 H
b10100 X
b10100 0
b10100 W
b10000 $
b10000 Z
18
#110
08
#115
b10100111111111111111111111010 -
b10100111111111111111111111010 I
b10100111111111111111111111010 O
b11000 Y
b10100 H
b11000 X
b11000 0
b11000 W
b10100 $
b10100 Z
18
#120
08
#125
1!
11
b1000 V
b0 -
b0 I
b0 O
1+
b101 &
b101 T
b11111111111111111111111111111010 /
b111111111111111111111010 .
b100 Y
b11000 H
b10100111111111111111111111010 ,
b10100111111111111111111111010 P
b11100 X
b100 0
b100 W
b11000 $
b11000 Z
18
#130
08
#135
0!
01
b1000111111111111111111111111 -
b1000111111111111111111111111 I
b1000111111111111111111111111 O
b0 V
b100 H
b1000 Y
0+
b0 &
b0 T
b0 /
b0 .
b1000 X
b1000 0
b1000 W
b100 $
b100 Z
b0 ,
b0 P
18
#140
08
#145
b10 6
b10 @
b10 G
b10 Q
b10 C
b11111111111111111111111111111111 E
b11111111111111111111111111111111 %
b11111111111111111111111111111111 B
1"
12
b11000000 V
b0 -
b0 I
b0 O
b10 &
b10 T
b11111111111111111111111111111111 /
b111111111111111111111111 .
b1100 Y
b1000 H
b1000111111111111111111111111 ,
b1000111111111111111111111111 P
b1100 X
b1000 0
b1000 W
b1000 $
b1000 Z
18
#150
08
#155
b0 E
0"
02
b0 %
b0 B
b0 V
b10 6
b10 @
b10 G
b10 Q
b10000 Y
b1100 H
b0 &
b0 T
b0 /
b0 .
b10 C
b10 7
b10 ?
b10 D
b10 S
b10000 X
b10000 0
b10000 W
b1100 $
b1100 Z
b0 ,
b0 P
18
#160
08
#165
b10100 Y
b10000 H
b10100 X
b10100 0
b10100 W
b10000 $
b10000 Z
18
#170
08
#175
b10100111111111111111111111010 -
b10100111111111111111111111010 I
b10100111111111111111111111010 O
b11000 Y
b10100 H
b11000 X
b11000 0
b11000 W
b10100 $
b10100 Z
18
#180
08
#185
1!
11
b1000 V
b0 -
b0 I
b0 O
1+
b101 &
b101 T
b11111111111111111111111111111010 /
b111111111111111111111010 .
b100 Y
b11000 H
b10100111111111111111111111010 ,
b10100111111111111111111111010 P
b11100 X
b100 0
b100 W
b11000 $
b11000 Z
18
#190
08
#195
0!
01
b1000111111111111111111111111 -
b1000111111111111111111111111 I
b1000111111111111111111111111 O
b0 V
b100 H
b1000 Y
0+
b0 &
b0 T
b0 /
b0 .
b1000 X
b1000 0
b1000 W
b100 $
b100 Z
b0 ,
b0 P
18
#200
08
#205
b1 6
b1 @
b1 G
b1 Q
b1 C
b11111111111111111111111111111111 E
b11111111111111111111111111111111 %
b11111111111111111111111111111111 B
1"
12
b11000000 V
b0 -
b0 I
b0 O
b10 &
b10 T
b11111111111111111111111111111111 /
b111111111111111111111111 .
b1100 Y
b1000 H
b1000111111111111111111111111 ,
b1000111111111111111111111111 P
b1100 X
b1000 0
b1000 W
b1000 $
b1000 Z
18
#210
08
#215
b0 E
0"
02
b0 %
b0 B
b0 V
05
b1 6
b1 @
b1 G
b1 Q
b10000 Y
b1100 H
b0 &
b0 T
b0 /
b0 .
b1 C
b1 7
b1 ?
b1 D
b1 S
b10000 X
b10000 0
b10000 W
b1100 $
b1100 Z
b0 ,
b0 P
18
#220
08
#225
b10100 Y
b10000 H
b10100 X
b10100 0
b10100 W
b10000 $
b10000 Z
18
#230
08
#235
b10100111111111111111111111010 -
b10100111111111111111111111010 I
b10100111111111111111111111010 O
b11000 Y
b10100 H
b11000 X
b11000 0
b11000 W
b10100 $
b10100 Z
18
#240
08
#245
1!
11
b1000 V
b0 -
b0 I
b0 O
1+
b101 &
b101 T
b11111111111111111111111111111010 /
b111111111111111111111010 .
b100 Y
b11000 H
b10100111111111111111111111010 ,
b10100111111111111111111111010 P
b11100 X
b100 0
b100 W
b11000 $
b11000 Z
18
#250
08
#255
0!
01
b1000111111111111111111111111 -
b1000111111111111111111111111 I
b1000111111111111111111111111 O
b0 V
b100 H
b1000 Y
0+
b0 &
b0 T
b0 /
b0 .
b1000 X
b1000 0
b1000 W
b100 $
b100 Z
b0 ,
b0 P
18
#260
08
#265
15
b0 6
b0 @
b0 G
b0 Q
b0 C
b11111111111111111111111111111111 E
b11111111111111111111111111111111 %
b11111111111111111111111111111111 B
1"
12
b11000000 V
b0 -
b0 I
b0 O
b10 &
b10 T
b11111111111111111111111111111111 /
b111111111111111111111111 .
b1100 Y
b1000 H
b1000111111111111111111111111 ,
b1000111111111111111111111111 P
b1100 X
b1000 0
b1000 W
b1000 $
b1000 Z
18
#270
08
#275
b0 E
0"
02
b0 %
b0 B
b0 V
15
b0 6
b0 @
b0 G
b0 Q
b10000 Y
b1100 H
b0 &
b0 T
b0 /
b0 .
b0 C
b0 7
b0 ?
b0 D
b0 S
b10000 X
b10000 0
b10000 W
b1100 $
b1100 Z
b0 ,
b0 P
1;
18
#280
08
#285
b10100 Y
b10000 H
b10100 X
b10100 0
b10100 W
b10000 $
b10000 Z
18
#290
08
#295
b10100111111111111111111111010 -
b10100111111111111111111111010 I
b10100111111111111111111111010 O
b11000 Y
b10100 H
b11000 X
b11000 0
b11000 W
b10100 $
b10100 Z
18
#300
08
#305
11
b1000 V
b0 -
b0 I
b0 O
1+
b101 &
b101 T
b11111111111111111111111111111010 /
b111111111111111111111010 .
b11100 Y
b11000 H
b10100111111111111111111111010 ,
b10100111111111111111111111010 P
b11100 X
b100 0
b100 W
b11000 $
b11000 Z
18
