imem_ireg/ireg.sv
module instr_reg (
    input  logic        clk,
    input  logic        reset,
    input  logic        en,     // Connect to ~stallD
    input  logic        clear,  // Connect to flushD
    input  logic [31:0] instr_in,
    output logic [31:0] instr_out
);

    always_ff @(posedge clk or posedge reset) begin
        if (reset) begin
            instr_out <= 32'b0;
        end else if (en) begin
            if (clear) 
                instr_out <= 32'b0; // Convert instruction to a NOP
            else 
                instr_out <= instr_in;
        end
    end

endmodule

imem_ireg/imem.sv
module instr_mem #(
    parameter n = 32, 
    parameter r = 8
)(
    input  logic [(r-1):0] addr,
    output logic [(n-1):0] readdata
);

    logic [n-1:0] RAM [0:(2**r)-1];

    initial begin
        // Zero out memory to prevent 'X' in GTKWave for unwritten spots
        for (int i = 0; i < (2**r); i++) begin
            RAM[i] = {n{1'b0}};
        end
        
        // Load the hex file
        $readmemh("test_prog.hex", RAM);
    end

    // 3. Indexing Logic
    // Use addr[(r-1):2] IF PC increments by 4 (Byte-addressed)
    // Use addr[(r-1):0] IF PC increments by 1 (Word-addressed)
    assign readdata = RAM[addr[(r-1):2]];

endmodule

single_cycle_spu/PC.sv
module pc (
    input wire clk,
    input wire reset,
    input wire stall,              // for pipeline (can tie to 0 for now)
    input wire branch_taken,
    input wire [31:0] branch_target,
    output reg [31:0] pc_out
);

wire [31:0] pc_plus4;
assign pc_plus4 = pc_out + 32'd4;

wire [31:0] next_pc;
assign next_pc = branch_taken ? branch_target : pc_plus4;

always @(posedge clk or posedge reset) begin
    if (reset)
        pc_out <= 32'd0;
    else if (!stall)
        pc_out <= next_pc;
end

endmodule

dmem.sv
module dmem(
    input  logic        clk,
    input  logic        we,   // memwrite from maindec
    input  logic [31:0] a,    // address from alu_out
    input  logic [31:0] wd,   // write data from acc_val
    output logic [31:0] rd    // read data
);

  logic [31:0] RAM[63:0]; // 64 words of memory

  // Read is combinational
  assign rd = RAM[a[31:2]]; 

  // Write is synchronous
  always_ff @(posedge clk)
    if (we) RAM[a[31:2]] <= wd;

endmodule

single_cycle_cpu/alu.sv
module alu
    #(parameter bitWidth = 32)(
    input  logic [(bitWidth-1):0] input1, input2,
    input  logic [3:0]  alucontrol,
    output logic [(bitWidth-1):0] result,
    output logic        zero
);

    logic [(bitWidth-1):0] condinvb, sumSlt;

    assign zero = (result == {bitWidth{1'b0}});
    assign condinvb = alucontrol[2] ? ~input2 : input2;
    assign sumSlt = input1 + condinvb + alucontrol[2];

    always @(*) begin
        case (alucontrol)
            4'b0000: result = input1 & input2;              // and
            4'b0001: result = input1 | input2;              // or
            4'b0010: result = input1 + input2;              // add
            4'b0011: result = ~(input1 | input2);           // nor
            4'b0110: result = sumSlt;                       // sub
            4'b0111: begin                                  // slt
                if (input1[31] != input2[31])
                    result = input1[31] ? 1 : 0;
                else
                    result = (input1 < input2) ? 1 : 0;
            end
            // Accumulator: mult/div are fully combinational; ACC receives lower 32 bits, we dont need separate mflo/mfhi instructions
            4'b1000: result = input1 * input2;              // mult (lower 32 bits → ACC)
            4'b1001: result = input1 / input2;              // div  (quotient → ACC)
	    4'b1111: result =  input2; //

            default: result = {bitWidth{1'b0}};
        endcase
    end

endmodule

acc.sv
// ACCUMULATOR 

module acc #(parameter n = 32)(
    input  logic         clk,
    input  logic         reset,
    input  logic         en,      // Write Enable from Controller
    input  logic [n-1:0] d,       // Data from ALU or Memory
    output logic [n-1:0] q        // Current Accumulator Value
);

    always_ff @(posedge clk or posedge reset) begin
        if (reset) 
            q <= {n{1'b0}};
        else if (en) 
            q <= d;
    end

endmodule

aludec.sv
module aludec(
    input  logic [1:0] aluop,
    output logic [3:0] alucontrol
);

    always_comb begin
        case (aluop)
            2'b00: alucontrol = 4'b0010; // ADD
            2'b01: alucontrol = 4'b0110; // SUB (used for branch comparison)
            2'b10: alucontrol = 4'b1000; // MULT
            2'b11: alucontrol = 4'b1001; // DIV
            default: alucontrol = 4'b0010;
        endcase
    end
endmodule

maindec.sv
module maindec(
    input  logic       reset,
    input  logic [5:0] op,
    output logic       memtoreg, memwrite,
    output logic       branch, alusrc,
    output logic       regwrite, jump,
    output logic [1:0] aluop 
);
    logic [7:0] controls;
    assign {regwrite, alusrc, memtoreg, memwrite, branch, jump, aluop} = controls;

    always_comb begin
        if (reset) controls = 8'b00000000;
        else begin
            case(op)
                // alusrc=0 ensures check Acc, not Acc vs Offset
                6'h04:   controls = 8'b0_0_0_0_1_0_00; // BZ
                6'h08:   controls = 8'b1_1_1_0_0_0_00; // LDA
                6'h02:   controls = 8'b1_1_0_0_0_0_00; // ADD
                6'h10:   controls = 8'b1_1_0_0_0_0_10; // MULT
                6'h12:   controls = 8'b1_1_0_0_0_0_11; // DIV
                6'h2B:   controls = 8'b0_1_0_1_0_0_00; // STA
                default: controls = 8'b0_0_0_0_0_0_00; // NOP
            endcase
        end
    end
endmodule

fetch_tb.sv
module fetch_tb;

    reg clk;
    reg reset;
    reg stall;
    reg zero_reg; // Sequential register to bridge the timing gap

    // --- Branch & Control Signals ---
    wire branch_taken;      
    wire [31:0] branch_target;
    wire alu_zero;          
    wire regwrite, alusrc, memtoreg, memwrite, branch, jump;
    wire [1:0] aluop;       
    wire [3:0] alucontrol;  

    // --- Data & Instruction Wires ---
    wire [31:0] pc_out;
    wire [31:0] instr;
    wire [31:0] ir_out;
    wire [31:0] acc_val;
    wire [31:0] alu_out;
    wire [31:0] operand2;
    wire [31:0] read_data; 
    wire [31:0] imm_ext;

    // --- Combinational Logic ---
    wire [23:0] immediateD = ir_out[23:0];
    wire [5:0]  opcodeD    = ir_out[31:26];

    // Synchronized Branch Logic: uses zero_reg from previous cycle
    assign branch_taken = branch & zero_reg;

    // Sign-extend immediate and calculate target
    assign imm_ext = {{8{immediateD[23]}}, immediateD};
    assign branch_target = (pc_out + 4) + (imm_ext << 2);

    // Operand2 Multiplexer (ALUSRC logic)
    assign operand2 = alusrc ? {{8{ir_out[23]}}, ir_out[23:0]} : 32'b0;

    // --- Module Instantiations ---

    maindec md (
        .reset(reset),
        .op(opcodeD),
        .regwrite(regwrite),
        .alusrc(alusrc),
        .memtoreg(memtoreg),
        .memwrite(memwrite),
        .branch(branch),
        .jump(jump),
        .aluop(aluop)
    );

    aludec ad (
        .aluop(aluop),
        .alucontrol(alucontrol)
    );

    acc #(.n(32)) main_acc (
        .clk(clk),
        .reset(reset),
        .en(regwrite),
        .d(alu_out),
        .q(acc_val)
    );

    alu #(.bitWidth(32)) dut_alu (
        .input1(acc_val),
        .input2(operand2),
        .alucontrol(alucontrol),
        .result(alu_out),
        .zero(alu_zero)
    );

    dmem data_mem (
        .clk(clk),
        .we(memwrite),
        .a(alu_out),
        .wd(acc_val),
        .rd(read_data)
    );

    pc pc_inst (
        .clk(clk),
        .reset(reset),
        .stall(stall),
        .branch_taken(branch_taken),
        .branch_target(branch_target),
        .pc_out(pc_out)
    );

    instr_mem imem (
        .addr(pc_out[7:0]),
        .readdata(instr)
    );

    instr_reg ir (
        .clk(clk),
        .reset(reset),
        .en(1'b1),
        .clear(1'b0),
        .instr_in(instr),
        .instr_out(ir_out)
    );

    // --- Clock & Reset Generation ---

    initial begin
        clk = 0;
        forever #5 clk = ~clk;
    end

    initial begin
        reset = 1;
        stall = 0;
        #12 reset = 0;
        #200 $finish;
    end

    // --- Logic for Flag Synchronization ---

    always @(posedge clk or posedge reset) begin
        if (reset) 
            zero_reg <= 0;
        else
            zero_reg <= alu_zero; 
    end

// --- Enhanced Debug Logging ---
initial begin
    $display("\nTime | PC_OUT   | IR_OUT   | ACC_VAL  | ALU_OUT  | REGW | BR | ZERO_R | TAKEN | TARGET");
    $display("------------------------------------------------------------------------------------------");
    forever @(negedge clk) begin // Logging on negedge captures values after the clock transition
        $display("%4t | %h | %h | %h | %h |  %b   | %b  |   %b    |   %b   | %h", 
            $time, 
            pc_out, 
            ir_out, 
            acc_val, 
            alu_out, 
            regwrite, 
            branch, 
            zero_reg, 
            branch_taken, 
            branch_target
        );
    end
end

    initial begin
        $dumpfile("fetch.vcd");
        $dumpvars(0, fetch_tb);
    end

endmodule

fetch.vcd
$date
	Wed May  6 19:49:53 2026
$end
$version
	Icarus Verilog
$end
$timescale
	1s
$end
$scope module fetch_tb $end
$var wire 1 ! branch_taken $end
$var wire 1 " regwrite $end
$var wire 32 # read_data [31:0] $end
$var wire 32 $ pc_out [31:0] $end
$var wire 32 % operand2 [31:0] $end
$var wire 6 & opcodeD [5:0] $end
$var wire 1 ' memwrite $end
$var wire 1 ( memtoreg $end
$var wire 1 ) jump $end
$var wire 32 * ir_out [31:0] $end
$var wire 32 + instr [31:0] $end
$var wire 24 , immediateD [23:0] $end
$var wire 32 - imm_ext [31:0] $end
$var wire 32 . branch_target [31:0] $end
$var wire 1 / branch $end
$var wire 1 0 alusrc $end
$var wire 2 1 aluop [1:0] $end
$var wire 4 2 alucontrol [3:0] $end
$var wire 1 3 alu_zero $end
$var wire 32 4 alu_out [31:0] $end
$var wire 32 5 acc_val [31:0] $end
$var reg 1 6 clk $end
$var reg 1 7 reset $end
$var reg 1 8 stall $end
$var reg 1 9 zero_reg $end
$scope module ad $end
$var wire 2 : aluop [1:0] $end
$var reg 4 ; alucontrol [3:0] $end
$upscope $end
$scope module data_mem $end
$var wire 1 6 clk $end
$var wire 32 < rd [31:0] $end
$var wire 1 ' we $end
$var wire 32 = wd [31:0] $end
$var wire 32 > a [31:0] $end
$upscope $end
$scope module dut_alu $end
$var wire 4 ? alucontrol [3:0] $end
$var wire 32 @ input2 [31:0] $end
$var wire 1 3 zero $end
$var wire 32 A sumSlt [31:0] $end
$var wire 32 B input1 [31:0] $end
$var wire 32 C condinvb [31:0] $end
$var parameter 32 D bitWidth $end
$var reg 32 E result [31:0] $end
$upscope $end
$scope module imem $end
$var wire 8 F addr [7:0] $end
$var wire 32 G readdata [31:0] $end
$var parameter 32 H n $end
$var parameter 32 I r $end
$scope begin $ivl_for_loop0 $end
$var integer 32 J i [31:0] $end
$upscope $end
$upscope $end
$scope module ir $end
$var wire 1 K clear $end
$var wire 1 6 clk $end
$var wire 1 L en $end
$var wire 32 M instr_in [31:0] $end
$var wire 1 7 reset $end
$var reg 32 N instr_out [31:0] $end
$upscope $end
$scope module main_acc $end
$var wire 1 6 clk $end
$var wire 32 O d [31:0] $end
$var wire 1 7 reset $end
$var wire 1 " en $end
$var parameter 32 P n $end
$var reg 32 Q q [31:0] $end
$upscope $end
$scope module md $end
$var wire 6 R op [5:0] $end
$var wire 1 7 reset $end
$var wire 1 " regwrite $end
$var wire 1 ' memwrite $end
$var wire 1 ( memtoreg $end
$var wire 1 ) jump $end
$var wire 1 / branch $end
$var wire 1 0 alusrc $end
$var wire 2 S aluop [1:0] $end
$var reg 8 T controls [7:0] $end
$upscope $end
$scope module pc_inst $end
$var wire 1 ! branch_taken $end
$var wire 32 U branch_target [31:0] $end
$var wire 1 6 clk $end
$var wire 1 7 reset $end
$var wire 1 8 stall $end
$var wire 32 V pc_plus4 [31:0] $end
$var wire 32 W next_pc [31:0] $end
$var reg 32 X pc_out [31:0] $end
$upscope $end
$upscope $end
$enddefinitions $end
$comment Show the parameter values. $end
$dumpall
b100000 P
b1000 I
b100000 H
b100000 D
$end
#0
$dumpvars
b0 X
b100 W
b100 V
b100 U
b0 T
b0 S
b0 R
b0 Q
b0 O
b0 N
b100000000000000000000000000101 M
1L
0K
b100000000 J
b100000000000000000000000000101 G
b0 F
b0 E
b0 C
b0 B
b0 A
b0 @
b10 ?
b0 >
b0 =
bx <
b10 ;
b0 :
x9
08
17
06
b0 5
b0 4
13
b10 2
b0 1
00
0/
b100 .
b0 -
b0 ,
b100000000000000000000000000101 +
b0 *
0)
0(
0'
b0 &
b0 %
b0 $
bx #
0"
0!
$end
#5
09
16
#10
06
#12
07
#15
03
b101 4
b101 >
b101 E
b101 O
b101 A
b101 C
b101 %
b101 @
1"
10
1(
b1000111111111111111111111011 +
b1000111111111111111111111011 G
b1000111111111111111111111011 M
b11100000 T
b1000 W
b100 F
b1000 &
b1000 R
b101 -
b101 ,
b1000 V
b11100 .
b11100 U
b100 $
b100 X
b100000000000000000000000000101 *
b100000000000000000000000000101 N
19
16
#20
06
#25
13
b11111111111111111111111111111011 C
0(
b11111111111111111111111111111011 %
b11111111111111111111111111111011 @
b11000000 T
b0 +
b0 G
b0 M
b10 &
b10 R
b11111111111111111111111111111011 -
b111111111111111111111011 ,
b1100 W
b1000 F
b0 4
b0 >
b0 E
b0 O
09
b1000111111111111111111111011 *
b1000111111111111111111111011 N
b1100 V
b11111111111111111111111111111000 .
b11111111111111111111111111111000 U
b1000 $
b1000 X
b0 A
b101 5
b101 =
b101 B
b101 Q
16
#30
06
#35
b0 C
0"
00
b0 %
b0 @
b0 T
13
b0 4
b0 >
b0 E
b0 O
b10000 W
b1100 F
b0 &
b0 R
b0 -
b0 ,
b0 A
b0 5
b0 =
b0 B
b0 Q
b10000 V
b10000 .
b10000 U
b1100 $
b1100 X
b0 *
b0 N
19
16
#40
06
#45
b10000111111111111111111111010 +
b10000111111111111111111111010 G
b10000111111111111111111111010 M
b10100 W
b10000 F
b10100 V
b10100 .
b10100 U
b10000 $
b10000 X
16
#50
06
#55
1!
1/
b0 +
b0 G
b0 M
b1000 T
b0 W
b10100 F
b100 &
b100 R
b11111111111111111111111111111010 -
b111111111111111111111010 ,
b11000 V
b0 .
b0 U
b10100 $
b10100 X
b10000111111111111111111111010 *
b10000111111111111111111111010 N
16
#60
06
#65
0!
0/
b0 T
b100000000000000000000000000101 +
b100000000000000000000000000101 G
b100000000000000000000000000101 M
b0 &
b0 R
b0 -
b0 ,
b0 F
b100 W
b0 *
b0 N
b100 V
b100 .
b100 U
b0 $
b0 X
16
#70
06
#75
03
b101 4
b101 >
b101 E
b101 O
b101 A
b101 C
b101 %
b101 @
1"
10
1(
b1000111111111111111111111011 +
b1000111111111111111111111011 G
b1000111111111111111111111011 M
b11100000 T
b1000 W
b100 F
b1000 &
b1000 R
b101 -
b101 ,
b1000 V
b11100 .
b11100 U
b100 $
b100 X
b100000000000000000000000000101 *
b100000000000000000000000000101 N
16
#80
06
#85
13
b11111111111111111111111111111011 C
0(
b11111111111111111111111111111011 %
b11111111111111111111111111111011 @
b11000000 T
b0 +
b0 G
b0 M
b10 &
b10 R
b11111111111111111111111111111011 -
b111111111111111111111011 ,
b1100 W
b1000 F
b0 4
b0 >
b0 E
b0 O
09
b1000111111111111111111111011 *
b1000111111111111111111111011 N
b1100 V
b11111111111111111111111111111000 .
b11111111111111111111111111111000 U
b1000 $
b1000 X
b0 A
b101 5
b101 =
b101 B
b101 Q
16
#90
06
#95
b0 C
0"
00
b0 %
b0 @
b0 T
13
b0 4
b0 >
b0 E
b0 O
b10000 W
b1100 F
b0 &
b0 R
b0 -
b0 ,
b0 A
b0 5
b0 =
b0 B
b0 Q
b10000 V
b10000 .
b10000 U
b1100 $
b1100 X
b0 *
b0 N
19
16
#100
06
#105
b10000111111111111111111111010 +
b10000111111111111111111111010 G
b10000111111111111111111111010 M
b10100 W
b10000 F
b10100 V
b10100 .
b10100 U
b10000 $
b10000 X
16
#110
06
#115
1!
1/
b0 +
b0 G
b0 M
b1000 T
b0 W
b10100 F
b100 &
b100 R
b11111111111111111111111111111010 -
b111111111111111111111010 ,
b11000 V
b0 .
b0 U
b10100 $
b10100 X
b10000111111111111111111111010 *
b10000111111111111111111111010 N
16
#120
06
#125
0!
0/
b0 T
b100000000000000000000000000101 +
b100000000000000000000000000101 G
b100000000000000000000000000101 M
b0 &
b0 R
b0 -
b0 ,
b0 F
b100 W
b0 *
b0 N
b100 V
b100 .
b100 U
b0 $
b0 X
16
#130
06
#135
03
b101 4
b101 >
b101 E
b101 O
b101 A
b101 C
b101 %
b101 @
1"
10
1(
b1000111111111111111111111011 +
b1000111111111111111111111011 G
b1000111111111111111111111011 M
b11100000 T
b1000 W
b100 F
b1000 &
b1000 R
b101 -
b101 ,
b1000 V
b11100 .
b11100 U
b100 $
b100 X
b100000000000000000000000000101 *
b100000000000000000000000000101 N
16
#140
06
#145
13
b11111111111111111111111111111011 C
0(
b11111111111111111111111111111011 %
b11111111111111111111111111111011 @
b11000000 T
b0 +
b0 G
b0 M
b10 &
b10 R
b11111111111111111111111111111011 -
b111111111111111111111011 ,
b1100 W
b1000 F
b0 4
b0 >
b0 E
b0 O
09
b1000111111111111111111111011 *
b1000111111111111111111111011 N
b1100 V
b11111111111111111111111111111000 .
b11111111111111111111111111111000 U
b1000 $
b1000 X
b0 A
b101 5
b101 =
b101 B
b101 Q
16
#150
06
#155
b0 C
0"
00
b0 %
b0 @
b0 T
13
b0 4
b0 >
b0 E
b0 O
b10000 W
b1100 F
b0 &
b0 R
b0 -
b0 ,
b0 A
b0 5
b0 =
b0 B
b0 Q
b10000 V
b10000 .
b10000 U
b1100 $
b1100 X
b0 *
b0 N
19
16
#160
06
#165
b10000111111111111111111111010 +
b10000111111111111111111111010 G
b10000111111111111111111111010 M
b10100 W
b10000 F
b10100 V
b10100 .
b10100 U
b10000 $
b10000 X
16
#170
06
#175
1!
1/
b0 +
b0 G
b0 M
b1000 T
b0 W
b10100 F
b100 &
b100 R
b11111111111111111111111111111010 -
b111111111111111111111010 ,
b11000 V
b0 .
b0 U
b10100 $
b10100 X
b10000111111111111111111111010 *
b10000111111111111111111111010 N
16
#180
06
#185
0!
0/
b0 T
b100000000000000000000000000101 +
b100000000000000000000000000101 G
b100000000000000000000000000101 M
b0 &
b0 R
b0 -
b0 ,
b0 F
b100 W
b0 *
b0 N
b100 V
b100 .
b100 U
b0 $
b0 X
16
#190
06
#195
03
b101 4
b101 >
b101 E
b101 O
b101 A
b101 C
b101 %
b101 @
1"
10
1(
b1000111111111111111111111011 +
b1000111111111111111111111011 G
b1000111111111111111111111011 M
b11100000 T
b1000 W
b100 F
b1000 &
b1000 R
b101 -
b101 ,
b1000 V
b11100 .
b11100 U
b100 $
b100 X
b100000000000000000000000000101 *
b100000000000000000000000000101 N
16
#200
06
#205
13
b11111111111111111111111111111011 C
0(
b11111111111111111111111111111011 %
b11111111111111111111111111111011 @
b11000000 T
b0 +
b0 G
b0 M
b10 &
b10 R
b11111111111111111111111111111011 -
b111111111111111111111011 ,
b1100 W
b1000 F
b0 4
b0 >
b0 E
b0 O
09
b1000111111111111111111111011 *
b1000111111111111111111111011 N
b1100 V
b11111111111111111111111111111000 .
b11111111111111111111111111111000 U
b1000 $
b1000 X
b0 A
b101 5
b101 =
b101 B
b101 Q
16
